{
  "last_run": "2026-04-19T22:31:47Z",
  "run_id": "24640709943",
  "comments_made": {},
  "prs_created": [
    {
      "branch": "repo-assist/improve-usage-docs-20260419",
      "title": "[Repo Assist] docs: rewrite usage.md for current CLI structure",
      "status": "pending_creation",
      "type": "docs"
    }
  ],
  "issues_actioned": {},
  "monthly_summary_issue": {
    "title": "[Repo Assist] Monthly Activity 2026-04",
    "number": 59,
    "month": "2026-04",
    "status": "open"
  },
  "backlog_cursor": {
    "issues": 72,
    "prs": 69
  },
  "checked_off_items": [
    "PR #61: perf(git) cache per-file commit data (merged)",
    "PR #62: fix(logging) clarify directory scan log fields (merged)",
    "Issue #58: duplicate of PR #61 (closed)"
  ],
  "notes": "PR #69 (feat: add legend) is open with all CI passing - ready for maintainer review. Issue #68 closed when PR #69 merges. Previous Repo Assist PRs #61 and #62 were merged. Issue #33 (Add Bubble visualization) was closed via PR #64 by maintainer. docs/usage.md was significantly out of date - rewrote for current CLI structure."
}
