{
  "last_run": "2026-07-08T15:01:00Z",
  "run_id": "28952600875",
  "monthly_summary_issue": 481,
  "backlog_cursor": 503,
  "comments_made": {
    "324": "2026-07-07", "329": "2026-07-04", "330": "2026-07-08",
    "333": "2026-06-20", "334": "2026-06-03", "335": "2026-06-01",
    "354": "2026-06-02", "355": "2026-06-02", "320": "2026-06-04",
    "373": "2026-06-08", "374": "2026-06-07", "385": "2026-06-11",
    "394": "2026-06-13", "402": "2026-06-20", "411": "2026-06-14",
    "416": "2026-06-19", "419": "2026-06-19", "421": "2026-06-20",
    "422": "2026-06-16", "429": "2026-06-24", "440": "2026-06-21",
    "442": "2026-06-21", "444": "2026-06-22", "445": "2026-06-26",
    "464": "2026-06-27", "471": "2026-06-28", "474": "2026-06-28",
    "503": "2026-07-06"
  },
  "open_prs": {
    "aw_pr_geometry_tests": {"branch": "repo-assist/test-bubbletree-geometry-20260708", "desc": "test(bubbletree): add unit tests for geometry.go and transforms.go - 24 new tests for enclosing-circle geometry and coordinate transform helpers"}
  },
  "issues_labelled": {
    "354": ["enhancement"], "355": ["bug"], "373": ["enhancement","refactor"],
    "374": ["enhancement"], "385": ["bug"], "402": ["enhancement"],
    "405": ["enhancement"], "421": ["enhancement"], "422": ["enhancement"],
    "423": ["enhancement"], "429": ["enhancement"], "440": ["bug"],
    "442": ["enhancement"], "444": ["bug"], "445": ["enhancement"],
    "464": ["enhancement"], "471": ["enhancement"],
    "474": ["enhancement","performance"]
  },
  "maintainer_preferences": [
    "Do not move helpers to new packages",
    "go.mod and go.sum are protected files - cannot be pushed by automation",
    ".github/workflows/release.yml is protected (see #388)",
    ".github/workflows/* are ALL protected - cannot be pushed by automation",
    "Keep PRs strictly scoped to description",
    "No backwards compatibility needed (pre-alpha tool)",
    "REJECTED: accumulator pattern with *[]T pointer parameters - maintainer called it 'nasty coupling' and 'short-sighted' (rejected PRs #488, #489, #507)"
  ],
  "closed_issues": [329, 421, 422, 423, 424, 402, 440, 444, 429, 445, 464],
  "closed_prs": [488, 489, 502, 507, 508, 509, 497, 499, 500, 501, 503, 504, 505, 506, 459, 460, 461, 469, 432, 438, 470, 473, 472, 475, 477, 479, 482, 462, 478, 480, 483, 484, 485, 465, 467, 487, 490, 491, 496, 498, 476],
  "notes": "Run 28952600875 (2026-07-08): Tasks 3->2 (no bug issues), 2, 4->5, 11. CRITICAL PREFERENCE CHANGE: maintainer rejected PRs #488, #489, #507 for using *[]T accumulator pattern - 'nasty coupling' and 'short-sighted'. Do NOT use accumulator pattern in future. PRs #508 (#perf-scatter) and #509 (#refactor-treemap) merged from previous run. PR #502 merged (SVG fillAttr). Task 2: Commented on #330 noting PR #502 merged and issue is fully resolved. Task 5: Created PR aw_pr_geometry_tests - 24 new tests for enclosing-circle geometry (geometry_test.go) and coordinate transforms (transforms_test.go) - these files were recently extracted from layout.go but had no direct tests. Issues #330 and #324 are ready to close."
}
